goatshell/__init__.py
goatshell/azure_cli.py
goatshell/completer.py
goatshell/confirm.py
goatshell/custom_keys.py
goatshell/dynamic_prompt.py
goatshell/fetch_goat.py
goatshell/goat_command_tree.json
goatshell/goatshell.py
goatshell/logger.py
goatshell/main.py
goatshell/misc.py
goatshell/parser.py
goatshell/settings_manager.py
goatshell/style.py
goatshell/switch_azure_subscription.py
goatshell/switch_profile.py
goatshell/toolbar.py
goatshell/ui.py
goatshell/data/aliyun.json
goatshell/data/aws.json
goatshell/data/az.json
goatshell/data/gcloud.json
goatshell/data/goat.json
goatshell/data/ibmcloud.json
goatshell/data/oci.json
goatshell/data/ovhai.json
goatshell-2024.7.16.1622.dist-info/LICENSE
goatshell-2024.7.16.1622.dist-info/METADATA
goatshell-2024.7.16.1622.dist-info/WHEEL
goatshell-2024.7.16.1622.dist-info/entry_points.txt
goatshell-2024.7.16.1622.dist-info/top_level.txt
goatshell-2024.7.16.1622.dist-info/RECORD
