Metadata-Version: 2.1
Name: goatshell
Version: 2024.7.16.1622
Summary: goatshell - goat shell interface to common cloud providers.
Author-email: Christopher Stacks <centerupt@gmail.com>
Classifier: Programming Language :: Python :: 3
Classifier: Operating System :: OS Independent
Requires-Python: >=3.7
License-File: LICENSE
Requires-Dist: prompt-toolkit >=3.0.0
Requires-Dist: Pygments <3.0.0,>=2.1.3
Requires-Dist: fuzzyfinder >=1.0.0
Requires-Dist: click >=8.0.4
Requires-Dist: goatconfigstore
Requires-Dist: goattoolbox
Requires-Dist: goatocitools
Requires-Dist: goatawstools
Requires-Dist: goataztools
Requires-Dist: goatibmcloudtools
Requires-Dist: goatovhaitools
Requires-Dist: goatjiratools
Requires-Dist: goatslacktools
Requires-Dist: goatjenkinstools
Requires-Dist: goaat
Requires-Dist: azure-cli
Requires-Dist: oci-cli
Requires-Dist: oci
Requires-Dist: aws2
